django_jaeger_middleware/__init__.py
django_jaeger_middleware/metadata.py
django_jaeger_middleware/middleware.py
django_jaeger_middleware-1.0.0.dist-info/LICENSE
django_jaeger_middleware-1.0.0.dist-info/METADATA
django_jaeger_middleware-1.0.0.dist-info/WHEEL
django_jaeger_middleware-1.0.0.dist-info/top_level.txt
django_jaeger_middleware-1.0.0.dist-info/RECORD
