Metadata-Version: 2.1
Name: django-jaeger-middleware
Version: 1.0.0
Summary: python(django) tracing middleware tool: django-jaeger-middleware
Home-page: https://github.com/GalphaXie/django-jaeger-middleware
Author: guang
Author-email: galphaxie@gmail.com
License: MIT
Download-URL: https://github.com/GalphaXie/django-jaeger-middleware
Keywords: django,jaeger,jaegertracing
Platform: UNKNOWN
Classifier: Framework :: Django
Classifier: Programming Language :: Python :: 3
Classifier: License :: OSI Approved :: MIT License
Classifier: Operating System :: OS Independent
Requires-Python: >=3.6
Requires-Dist: jaeger-client
Requires-Dist: opentracing
